{
  "dns": {
    "final": "local-dns",
    "rules": [
      {
        "clash_mode": "Global",
        "server": "proxy-dns",
        "source_ip_cidr": [
          "172.19.0.0/30"
        ]
      },
      {
        "server": "proxy-dns",
        "source_ip_cidr": [
          "172.19.0.0/30"
        ]
      },
      {
        "clash_mode": "Direct",
        "server": "direct-dns"
      },
      {
        "rule_set": [
          "geosite-ir"
        ],
        "server": "direct-dns"
      }
    ],
    "servers": [
      {
        "address": "tls://208.67.222.123",
        "address_resolver": "local-dns",
        "detour": "proxy",
        "tag": "proxy-dns"
      },
      {
        "address": "local",
        "detour": "direct",
        "tag": "local-dns"
      },
      {
        "address": "rcode://success",
        "tag": "block"
      },
      {
        "address": "local",
        "detour": "direct",
        "tag": "direct-dns"
      }
    ],
    "strategy": "prefer_ipv4"
  },
  "inbounds": [
    {
      "address": [
        "172.19.0.1/30",
        "fdfe:dcba:9876::1/126"
      ],
      "auto_route": true,
      "endpoint_independent_nat": false,
      "mtu": 9000,
      "platform": {
        "http_proxy": {
          "enabled": true,
          "server": "127.0.0.1",
          "server_port": 2080
        }
      },
      "sniff": true,
      "stack": "system",
      "strict_route": false,
      "type": "tun"
    },
    {
      "listen": "127.0.0.1",
      "listen_port": 2080,
      "sniff": true,
      "type": "mixed",
      "users": []
    }
  ],
  "outbounds": [
    {
      "tag": "proxy",
      "type": "selector",
      "outbounds": [
        "auto",
        "vless-9a327d11",
        "vless-28a47555",
        "vless-4b40aeb9",
        "vless-d427188c",
        "vless-467fd72e",
        "vless-4e210ac9",
        "vless-23bd18ab",
        "vless-2cc7f104",
        "vless-93474825",
        "vless-b2de4318",
        "vless-38c77651",
        "vless-73038710",
        "vless-032783e4",
        "vless-2c1ad536",
        "vless-a511b4e6",
        "vless-b8ba32d3",
        "vless-0bc12b76",
        "vless-40636c58",
        "vless-0a162f43",
        "vless-41e4c6cf",
        "vless-6c093b3a",
        "vless-e6af36ad",
        "vless-63f7d559",
        "vless-fc111539",
        "vless-f3da0ef1",
        "vless-0bf24c72",
        "vless-406e8c5b",
        "vless-3f648256",
        "vless-ab35bffa",
        "vless-89f428b2",
        "vless-e4942d69",
        "vless-7324e3cc",
        "vless-acfde351",
        "vless-596fbf85",
        "vless-e17d5fda",
        "vless-0b4e0e13",
        "trojan-d03f5255",
        "trojan-93a53dd8",
        "trojan-1c80afce",
        "trojan-18d24d78",
        "trojan-db806aa3",
        "trojan-4c293a6d",
        "trojan-eaaf6c7b",
        "trojan-e177bcf9",
        "trojan-a992ccdd",
        "trojan-c55d2cc0",
        "trojan-d5bee926",
        "trojan-6fd5968b",
        "trojan-6b1d7e9f",
        "trojan-3756643b",
        "trojan-df8a8d4f",
        "trojan-683a29cf",
        "trojan-82498354",
        "trojan-1899e9e3",
        "trojan-3e01f3db",
        "trojan-2bcee335",
        "trojan-25b3dee3",
        "trojan-1eb8b216",
        "trojan-b654ad3f",
        "trojan-3ecd6981",
        "trojan-69561504",
        "trojan-c9ed7635",
        "trojan-941d2d86",
        "trojan-cb72fcfb",
        "trojan-cb029561",
        "trojan-5fc7d7cf",
        "trojan-30193c19",
        "trojan-1991af5f",
        "trojan-9fe61287",
        "trojan-bda8a2b3",
        "trojan-b4358c28",
        "trojan-a03c0689",
        "trojan-f9af0c86",
        "trojan-5c71dcb3",
        "trojan-b7e3e5ba",
        "trojan-08ad8740",
        "trojan-b2683d17",
        "trojan-018b975c",
        "trojan-458a7d03",
        "trojan-dd146289",
        "trojan-6a490e74",
        "trojan-bb3e4825",
        "trojan-03977796",
        "trojan-d65f433b",
        "trojan-44511431",
        "trojan-89719fdf",
        "trojan-6ee7c0cf",
        "trojan-1c3881c7",
        "trojan-b95ad2a1",
        "trojan-badbd5db",
        "trojan-d08f85fb",
        "trojan-da109940",
        "vmess-9f769a26",
        "vmess-d327756c",
        "vmess-c7dfd907",
        "vmess-1afcf2b1",
        "vmess-3c1f5707",
        "vmess-c5736719",
        "vmess-a1618eaf",
        "vmess-c1dbd78a",
        "vmess-8909e1da",
        "vmess-2f01dd29",
        "vmess-b4de9c47",
        "vmess-5e9b34d3",
        "vmess-d339ac90",
        "vmess-5a87bcd1",
        "vmess-7c42f89f",
        "vmess-43638b48",
        "vmess-594c9990",
        "vmess-14851bde",
        "vmess-9fa11333",
        "vmess-5827f0b5",
        "vmess-ad2ab857",
        "vmess-daff147a",
        "vmess-131eb9bd",
        "vmess-a492dbd0",
        "vmess-a96b8e57",
        "vmess-f0d1ae9d",
        "vmess-cb26382d",
        "vmess-867e887c",
        "vmess-2934f66f",
        "vmess-567cf0cd",
        "vmess-47644e9d",
        "vmess-88231101",
        "vmess-1f3082ce",
        "vmess-d3644196",
        "vmess-22e7defb",
        "vmess-b6982826",
        "vmess-d3e94601",
        "vmess-adc3a4bb",
        "vmess-8ad6af4c",
        "vmess-29ce0955",
        "vmess-36658fda",
        "vmess-1d406b88",
        "vmess-01b3591b",
        "vmess-8e34a5b7",
        "vmess-75777faf",
        "vmess-96dbe91d",
        "vmess-fd33b1b5",
        "vmess-eed3b549",
        "vmess-bf404906",
        "vmess-75303389",
        "vmess-e82f6202",
        "vmess-13cc7caa",
        "vmess-b680d079",
        "vmess-11155bf3",
        "vmess-43e2e301",
        "vmess-9a3a33d1",
        "vmess-ab1961df",
        "vmess-99c9d086",
        "vmess-3b8b342c",
        "vmess-26d794a5",
        "vmess-2413b649",
        "vmess-2d76c876",
        "vmess-625b8630",
        "vmess-3f136e86",
        "vmess-40c58600",
        "vmess-0a2871c2",
        "vmess-e1fad008",
        "vmess-3a6ed001",
        "vmess-3b832077",
        "vmess-cc43adc2",
        "vmess-0aa52d2f",
        "vmess-fa200099",
        "vmess-f969b82d",
        "vmess-0d778cda",
        "vmess-7abf99ea",
        "vmess-5da67203",
        "vmess-965b19cc",
        "vmess-38c82027",
        "vmess-e3cd4280",
        "vmess-91dc83f3",
        "vmess-9a63d664",
        "vmess-527ac4a7",
        "vmess-f526d49c",
        "vmess-d5884270",
        "ss-7d8594b4",
        "ss-d3b11955",
        "ss-f07352d7",
        "ss-0de844c8",
        "direct"
      ]
    },
    {
      "tag": "auto",
      "type": "urltest",
      "outbounds": [
        "vless-9a327d11",
        "vless-28a47555",
        "vless-4b40aeb9",
        "vless-d427188c",
        "vless-467fd72e",
        "vless-4e210ac9",
        "vless-23bd18ab",
        "vless-2cc7f104",
        "vless-93474825",
        "vless-b2de4318",
        "vless-38c77651",
        "vless-73038710",
        "vless-032783e4",
        "vless-2c1ad536",
        "vless-a511b4e6",
        "vless-b8ba32d3",
        "vless-0bc12b76",
        "vless-40636c58",
        "vless-0a162f43",
        "vless-41e4c6cf",
        "vless-6c093b3a",
        "vless-e6af36ad",
        "vless-63f7d559",
        "vless-fc111539",
        "vless-f3da0ef1",
        "vless-0bf24c72",
        "vless-406e8c5b",
        "vless-3f648256",
        "vless-ab35bffa",
        "vless-89f428b2",
        "vless-e4942d69",
        "vless-7324e3cc",
        "vless-acfde351",
        "vless-596fbf85",
        "vless-e17d5fda",
        "vless-0b4e0e13",
        "trojan-d03f5255",
        "trojan-93a53dd8",
        "trojan-1c80afce",
        "trojan-18d24d78",
        "trojan-db806aa3",
        "trojan-4c293a6d",
        "trojan-eaaf6c7b",
        "trojan-e177bcf9",
        "trojan-a992ccdd",
        "trojan-c55d2cc0",
        "trojan-d5bee926",
        "trojan-6fd5968b",
        "trojan-6b1d7e9f",
        "trojan-3756643b",
        "trojan-df8a8d4f",
        "trojan-683a29cf",
        "trojan-82498354",
        "trojan-1899e9e3",
        "trojan-3e01f3db",
        "trojan-2bcee335",
        "trojan-25b3dee3",
        "trojan-1eb8b216",
        "trojan-b654ad3f",
        "trojan-3ecd6981",
        "trojan-69561504",
        "trojan-c9ed7635",
        "trojan-941d2d86",
        "trojan-cb72fcfb",
        "trojan-cb029561",
        "trojan-5fc7d7cf",
        "trojan-30193c19",
        "trojan-1991af5f",
        "trojan-9fe61287",
        "trojan-bda8a2b3",
        "trojan-b4358c28",
        "trojan-a03c0689",
        "trojan-f9af0c86",
        "trojan-5c71dcb3",
        "trojan-b7e3e5ba",
        "trojan-08ad8740",
        "trojan-b2683d17",
        "trojan-018b975c",
        "trojan-458a7d03",
        "trojan-dd146289",
        "trojan-6a490e74",
        "trojan-bb3e4825",
        "trojan-03977796",
        "trojan-d65f433b",
        "trojan-44511431",
        "trojan-89719fdf",
        "trojan-6ee7c0cf",
        "trojan-1c3881c7",
        "trojan-b95ad2a1",
        "trojan-badbd5db",
        "trojan-d08f85fb",
        "trojan-da109940",
        "vmess-9f769a26",
        "vmess-d327756c",
        "vmess-c7dfd907",
        "vmess-1afcf2b1",
        "vmess-3c1f5707",
        "vmess-c5736719",
        "vmess-a1618eaf",
        "vmess-c1dbd78a",
        "vmess-8909e1da",
        "vmess-2f01dd29",
        "vmess-b4de9c47",
        "vmess-5e9b34d3",
        "vmess-d339ac90",
        "vmess-5a87bcd1",
        "vmess-7c42f89f",
        "vmess-43638b48",
        "vmess-594c9990",
        "vmess-14851bde",
        "vmess-9fa11333",
        "vmess-5827f0b5",
        "vmess-ad2ab857",
        "vmess-daff147a",
        "vmess-131eb9bd",
        "vmess-a492dbd0",
        "vmess-a96b8e57",
        "vmess-f0d1ae9d",
        "vmess-cb26382d",
        "vmess-867e887c",
        "vmess-2934f66f",
        "vmess-567cf0cd",
        "vmess-47644e9d",
        "vmess-88231101",
        "vmess-1f3082ce",
        "vmess-d3644196",
        "vmess-22e7defb",
        "vmess-b6982826",
        "vmess-d3e94601",
        "vmess-adc3a4bb",
        "vmess-8ad6af4c",
        "vmess-29ce0955",
        "vmess-36658fda",
        "vmess-1d406b88",
        "vmess-01b3591b",
        "vmess-8e34a5b7",
        "vmess-75777faf",
        "vmess-96dbe91d",
        "vmess-fd33b1b5",
        "vmess-eed3b549",
        "vmess-bf404906",
        "vmess-75303389",
        "vmess-e82f6202",
        "vmess-13cc7caa",
        "vmess-b680d079",
        "vmess-11155bf3",
        "vmess-43e2e301",
        "vmess-9a3a33d1",
        "vmess-ab1961df",
        "vmess-99c9d086",
        "vmess-3b8b342c",
        "vmess-26d794a5",
        "vmess-2413b649",
        "vmess-2d76c876",
        "vmess-625b8630",
        "vmess-3f136e86",
        "vmess-40c58600",
        "vmess-0a2871c2",
        "vmess-e1fad008",
        "vmess-3a6ed001",
        "vmess-3b832077",
        "vmess-cc43adc2",
        "vmess-0aa52d2f",
        "vmess-fa200099",
        "vmess-f969b82d",
        "vmess-0d778cda",
        "vmess-7abf99ea",
        "vmess-5da67203",
        "vmess-965b19cc",
        "vmess-38c82027",
        "vmess-e3cd4280",
        "vmess-91dc83f3",
        "vmess-9a63d664",
        "vmess-527ac4a7",
        "vmess-f526d49c",
        "vmess-d5884270",
        "ss-7d8594b4",
        "ss-d3b11955",
        "ss-f07352d7",
        "ss-0de844c8"
      ],
      "url": "http://www.gstatic.com/generate_204",
      "interval": "10m",
      "tolerance": 50
    },
    {
      "tag": "direct",
      "type": "direct"
    },
    {
      "tag": "dns-out",
      "type": "dns"
    },
    {
      "tag": "block",
      "type": "block"
    },
    {
      "type": "vless",
      "tag": "vless-9a327d11",
      "server": "151.101.2.165",
      "server_port": 80,
      "uuid": "%54%45%4c%45%47%52%41%4d%2d%4e%55%46%69%4c%54%45%52%2d%33%30%31%31%61%35%36%35%65%30%31%62",
      "flow": "",
      "tls": {
        "enabled": true,
        "server_name": "151.101.2.165",
        "insecure": true
      },
      "transport": {
        "type": "ws",
        "path": "/telegram-NUFiLTER,telegram-NUFiLTER,telegram-NUFiLTER,telegram-NUFiLTER,telegram-NUFiLTER,telegram-NUFiLTER,telegram-NUFiLTER,telegram-NUFiLTER?ed=8080",
        "headers": {
          "Host": "6.fidsxss7x.ir"
        }
      }
    },
    {
      "type": "vless",
      "tag": "vless-28a47555",
      "server": "103.71.22.3",
      "server_port": 443,
      "uuid": "009cccba-c0ec-4297-9898-5115898a7246",
      "flow": "xtls-rprx-vision",
      "tls": {
        "enabled": true,
        "server_name": "spb33.hipay.su",
        "insecure": true
      },
      "transport": {}
    },
    {
      "type": "vless",
      "tag": "vless-4b40aeb9",
      "server": "103.71.22.3",
      "server_port": 443,
      "uuid": "009cccba-c0ec-4297-9898-5115898a7246",
      "flow": "xtls-rprx-vision",
      "tls": {
        "enabled": true,
        "server_name": "spb33.hipay.su",
        "insecure": true
      },
      "transport": {}
    },
    {
      "type": "vless",
      "tag": "vless-d427188c",
      "server": "103.71.22.3",
      "server_port": 443,
      "uuid": "009cccba-c0ec-4297-9898-5115898a7246",
      "flow": "xtls-rprx-vision",
      "tls": {
        "enabled": true,
        "server_name": "spb33.hipay.su",
        "insecure": true
      },
      "transport": {}
    },
    {
      "type": "vless",
      "tag": "vless-467fd72e",
      "server": "103.71.22.3",
      "server_port": 443,
      "uuid": "009cccba-c0ec-4297-9898-5115898a7246",
      "flow": "xtls-rprx-vision",
      "tls": {
        "enabled": true,
        "server_name": "spb33.hipay.su",
        "insecure": true
      },
      "transport": {}
    },
    {
      "type": "vless",
      "tag": "vless-4e210ac9",
      "server": "103.71.22.3",
      "server_port": 443,
      "uuid": "009cccba-c0ec-4297-9898-5115898a7246",
      "flow": "xtls-rprx-vision",
      "tls": {
        "enabled": true,
        "server_name": "spb33.hipay.su",
        "insecure": true
      },
      "transport": {}
    },
    {
      "type": "vless",
      "tag": "vless-23bd18ab",
      "server": "20.215.42.100",
      "server_port": 443,
      "uuid": "0466bf43-b8a3-4ddb-eb1c-5bec6e1ae692",
      "flow": "xtls-rprx-vision",
      "tls": {
        "enabled": true,
        "server_name": "eleven.dilik.co",
        "insecure": true
      },
      "transport": {}
    },
    {
      "type": "vless",
      "tag": "vless-2cc7f104",
      "server": "wear.net",
      "server_port": 443,
      "uuid": "046fd332-80a6-43b0-91b0-7238a1dfc36c",
      "flow": "",
      "tls": {
        "enabled": true,
        "server_name": "wear.net",
        "insecure": true
      },
      "transport": {
        "type": "ws",
        "path": "/?ed=MARAMBASHI_MARAMBASHI/?ed=2560",
        "headers": {
          "Host": "aw035.ir"
        }
      }
    },
    {
      "type": "vless",
      "tag": "vless-93474825",
      "server": "tgju.org",
      "server_port": 80,
      "uuid": "04cfc03e-6c57-4e9b-9417-8bb3a803db66",
      "flow": "",
      "tls": {
        "enabled": true,
        "server_name": "tgju.org",
        "insecure": true
      },
      "transport": {
        "type": "ws",
        "path": "/?ed=2048",
        "headers": {
          "Host": "aSsertIVe-InFoRmAtIoN.OnEeat.CO."
        }
      }
    },
    {
      "type": "vless",
      "tag": "vless-b2de4318",
      "server": "81.28.12.12",
      "server_port": 443,
      "uuid": "054d503d-4748-47a6-8118-71a96c51f2d9",
      "flow": "",
      "tls": {
        "enabled": true,
        "server_name": "gcore.com",
        "insecure": true
      },
      "transport": {
        "type": "ws",
        "path": "/VLESS",
        "headers": {
          "Host": "fr-2-vpr.maxima.us.kg"
        }
      }
    },
    {
      "type": "vless",
      "tag": "vless-38c77651",
      "server": "81.28.12.12",
      "server_port": 443,
      "uuid": "054d503d-4748-47a6-8118-71a96c51f2d9",
      "flow": "",
      "tls": {
        "enabled": true,
        "server_name": "gcore.lu",
        "insecure": true
      },
      "transport": {
        "type": "ws",
        "path": "/VLESS",
        "headers": {
          "Host": "nl-8sdsfrge.maxima.us.kg"
        }
      }
    },
    {
      "type": "vless",
      "tag": "vless-73038710",
      "server": "81.28.12.12",
      "server_port": 443,
      "uuid": "054d503d-4748-47a6-8118-71a96c51f2d9",
      "flow": "",
      "tls": {
        "enabled": true,
        "server_name": "gcore.lu",
        "insecure": true
      },
      "transport": {
        "type": "ws",
        "path": "/VLESS",
        "headers": {
          "Host": "nl-kseuo.maxima.us.kg"
        }
      }
    },
    {
      "type": "vless",
      "tag": "vless-032783e4",
      "server": "81.28.12.12",
      "server_port": 443,
      "uuid": "054d503d-4748-47a6-8118-71a96c51f2d9",
      "flow": "",
      "tls": {
        "enabled": true,
        "server_name": "gcore.lu",
        "insecure": true
      },
      "transport": {
        "type": "ws",
        "path": "/VLESS",
        "headers": {
          "Host": "nl50.maxima.us.kg"
        }
      }
    },
    {
      "type": "vless",
      "tag": "vless-2c1ad536",
      "server": "13.39.66.121",
      "server_port": 22222,
      "uuid": "05519058-d2ac-4f28-9e4a-2b2a1386749e",
      "flow": "",
      "tls": {
        "enabled": true,
        "server_name": "telegram-channel-vlessconfig.sohala.uk",
        "insecure": true
      },
      "transport": {
        "type": "ws",
        "path": "/telegram-channel-vlessconfig-ws",
        "headers": {
          "Host": "telegram-channel-vlessconfig.sohala.uk"
        }
      }
    },
    {
      "type": "vless",
      "tag": "vless-a511b4e6",
      "server": "15.222.231.31",
      "server_port": 22222,
      "uuid": "05519058-d2ac-4f28-9e4a-2b2a1386749e",
      "flow": "",
      "tls": {
        "enabled": true,
        "server_name": "telegram-channel-vlessconfig.sohala.uk",
        "insecure": true
      },
      "transport": {
        "type": "ws",
        "path": "/telegram-channel-vlessconfig-ws",
        "headers": {
          "Host": "telegram-channel-vlessconfig.sohala.uk"
        }
      }
    },
    {
      "type": "vless",
      "tag": "vless-b8ba32d3",
      "server": "3.11.146.233",
      "server_port": 22222,
      "uuid": "05519058-d2ac-4f28-9e4a-2b2a1386749e",
      "flow": "",
      "tls": {
        "enabled": true,
        "server_name": "telegram-channel-vlessconfig.sohala.uk",
        "insecure": true
      },
      "transport": {
        "type": "ws",
        "path": "/telegram-channel-vlessconfig-ws",
        "headers": {
          "Host": "telegram-channel-vlessconfig.sohala.uk"
        }
      }
    },
    {
      "type": "vless",
      "tag": "vless-0bc12b76",
      "server": "3.210.149.201",
      "server_port": 22222,
      "uuid": "05519058-d2ac-4f28-9e4a-2b2a1386749e",
      "flow": "",
      "tls": {
        "enabled": true,
        "server_name": "telegram-channel-vlessconfig.sohala.uk",
        "insecure": true
      },
      "transport": {
        "type": "ws",
        "path": "/telegram-channel-vlessconfig-ws",
        "headers": {
          "Host": "telegram-channel-vlessconfig.sohala.uk"
        }
      }
    },
    {
      "type": "vless",
      "tag": "vless-40636c58",
      "server": "3.215.172.82",
      "server_port": 22222,
      "uuid": "05519058-d2ac-4f28-9e4a-2b2a1386749e",
      "flow": "",
      "tls": {
        "enabled": true,
        "server_name": "telegram-channel-vlessconfig.sohala.uk",
        "insecure": true
      },
      "transport": {
        "type": "ws",
        "path": "/telegram-channel-vlessconfig-ws",
        "headers": {
          "Host": "telegram-channel-vlessconfig.sohala.uk"
        }
      }
    },
    {
      "type": "vless",
      "tag": "vless-0a162f43",
      "server": "3.98.177.63",
      "server_port": 22222,
      "uuid": "05519058-d2ac-4f28-9e4a-2b2a1386749e",
      "flow": "",
      "tls": {
        "enabled": true,
        "server_name": "telegram-channel-vlessconfig.sohala.uk",
        "insecure": true
      },
      "transport": {
        "type": "ws",
        "path": "/telegram-channel-vlessconfig-ws",
        "headers": {
          "Host": "telegram-channel-vlessconfig.sohala.uk"
        }
      }
    },
    {
      "type": "vless",
      "tag": "vless-41e4c6cf",
      "server": "3.98.177.63",
      "server_port": 22222,
      "uuid": "05519058-d2ac-4f28-9e4a-2b2a1386749e",
      "flow": "",
      "tls": {
        "enabled": true,
        "server_name": "telegram-channel-vlessconfig.sohala.uk",
        "insecure": true
      },
      "transport": {
        "type": "ws",
        "path": "/telegram-channel-vlessconfig-ws",
        "headers": {
          "Host": "telegram-channel-vlessconfig.sohala.uk"
        }
      }
    },
    {
      "type": "vless",
      "tag": "vless-6c093b3a",
      "server": "44.209.119.18",
      "server_port": 22222,
      "uuid": "05519058-d2ac-4f28-9e4a-2b2a1386749e",
      "flow": "",
      "tls": {
        "enabled": true,
        "server_name": "telegram-channel-vlessconfig.sohala.uk",
        "insecure": true
      },
      "transport": {
        "type": "ws",
        "path": "/telegram-channel-vlessconfig-ws",
        "headers": {
          "Host": "telegram-channel-vlessconfig.sohala.uk"
        }
      }
    },
    {
      "type": "vless",
      "tag": "vless-e6af36ad",
      "server": "51.44.147.208",
      "server_port": 22222,
      "uuid": "05519058-d2ac-4f28-9e4a-2b2a1386749e",
      "flow": "",
      "tls": {
        "enabled": true,
        "server_name": "telegram-channel-vlessconfig.sohala.uk",
        "insecure": true
      },
      "transport": {
        "type": "ws",
        "path": "/telegram-channel-vlessconfig-ws",
        "headers": {
          "Host": "telegram-channel-vlessconfig.sohala.uk"
        }
      }
    },
    {
      "type": "vless",
      "tag": "vless-63f7d559",
      "server": "51.44.191.123",
      "server_port": 22222,
      "uuid": "05519058-d2ac-4f28-9e4a-2b2a1386749e",
      "flow": "",
      "tls": {
        "enabled": true,
        "server_name": "telegram-channel-vlessconfig.sohala.uk",
        "insecure": true
      },
      "transport": {
        "type": "ws",
        "path": "/telegram-channel-vlessconfig-ws",
        "headers": {
          "Host": "telegram-channel-vlessconfig.sohala.uk"
        }
      }
    },
    {
      "type": "vless",
      "tag": "vless-fc111539",
      "server": "54.76.219.66",
      "server_port": 22222,
      "uuid": "05519058-d2ac-4f28-9e4a-2b2a1386749e",
      "flow": "",
      "tls": {
        "enabled": true,
        "server_name": "telegram-channel-vlessconfig.sohala.uk",
        "insecure": true
      },
      "transport": {
        "type": "ws",
        "path": "/telegram-channel-vlessconfig-ws",
        "headers": {
          "Host": "telegram-channel-vlessconfig.sohala.uk"
        }
      }
    },
    {
      "type": "vless",
      "tag": "vless-f3da0ef1",
      "server": "81.28.12.12",
      "server_port": 443,
      "uuid": "06cc6ba6-b10c-5bd9-91dd-8e6f72fcf970",
      "flow": "",
      "tls": {
        "enabled": true,
        "server_name": "gcore.lu",
        "insecure": true
      },
      "transport": {
        "type": "ws",
        "path": "/vless",
        "headers": {
          "Host": "nl-argetgrwt.maxima.us.kg"
        }
      }
    },
    {
      "type": "vless",
      "tag": "vless-0bf24c72",
      "server": "91.107.131.93",
      "server_port": 2053,
      "uuid": "08aa8e13-d639-4b24-9a7a-c2e56ee0beaa",
      "flow": "xtls-rprx-vision",
      "tls": {
        "enabled": true,
        "server_name": "yahoo.com",
        "insecure": true
      },
      "transport": {}
    },
    {
      "type": "vless",
      "tag": "vless-406e8c5b",
      "server": "15.204.187.172",
      "server_port": 443,
      "uuid": "0a44145f-59dc-4e5b-a233-677b97f5114c",
      "flow": "",
      "tls": {
        "enabled": true,
        "server_name": "147135011033.sec21org.com",
        "insecure": true
      },
      "transport": {}
    },
    {
      "type": "vless",
      "tag": "vless-3f648256",
      "server": "tgju.org",
      "server_port": 80,
      "uuid": "0bdf9b9f-9a00-41b3-8bc1-80ab0969805e",
      "flow": "",
      "tls": {
        "enabled": true,
        "server_name": "tgju.org",
        "insecure": true
      },
      "transport": {
        "type": "ws",
        "path": "/?ed=2048",
        "headers": {
          "Host": "CALM-GIFt.ONeeAT.cO."
        }
      }
    },
    {
      "type": "vless",
      "tag": "vless-ab35bffa",
      "server": "23.227.39.185",
      "server_port": 8080,
      "uuid": "0c04dd79-71ad-475e-9a22-8fe625afccbb",
      "flow": "",
      "tls": {
        "enabled": true,
        "server_name": "23.227.39.185",
        "insecure": true
      },
      "transport": {
        "type": "ws",
        "path": "/telegram,ELiV2RAY-telegram,ELiV2RAY-telegram,ELiV2RAY-telegram,ELiV2RAY-telegram,ELiV2RAY-telegram,ELiV2RAY?ed=2560",
        "headers": {
          "Host": "seyyed.webdade.ip-ddns.com"
        }
      }
    },
    {
      "type": "vless",
      "tag": "vless-89f428b2",
      "server": "ZuLa.ir",
      "server_port": 8080,
      "uuid": "0c04dd79-71ad-475e-9a22-8fe625afccbb",
      "flow": "",
      "tls": {
        "enabled": true,
        "server_name": "ZuLa.ir",
        "insecure": true
      },
      "transport": {
        "type": "ws",
        "path": "/telegram---VPNCUSTOMIZE--telegram--VPNCUSTOMIZE--telegram--VPNCUSTOMIZE--telegram--VPNCUSTOMIZE--telegram----VPNCUSTOMIZE?ed=2048",
        "headers": {
          "Host": "seyyed.webdade.ip-ddns.com"
        }
      }
    },
    {
      "type": "vless",
      "tag": "vless-e4942d69",
      "server": "ZuLa.ir",
      "server_port": 8080,
      "uuid": "0c04dd79-71ad-475e-9a22-8fe625afccbb",
      "flow": "",
      "tls": {
        "enabled": true,
        "server_name": "ZuLa.ir",
        "insecure": true
      },
      "transport": {
        "type": "ws",
        "path": "/telegram---VPNCUSTOMIZE--telegram--VPNCUSTOMIZE--telegram--VPNCUSTOMIZE--telegram--VPNCUSTOMIZE--telegram----VPNCUSTOMIZE?ed=2048",
        "headers": {
          "Host": "seyyed.webdade.ip-ddns.com"
        }
      }
    },
    {
      "type": "vless",
      "tag": "vless-7324e3cc",
      "server": "ZuLa.ir",
      "server_port": 8080,
      "uuid": "0c04dd79-71ad-475e-9a22-8fe625afccbb",
      "flow": "",
      "tls": {
        "enabled": true,
        "server_name": "ZuLa.ir",
        "insecure": true
      },
      "transport": {
        "type": "ws",
        "path": "/telegram---VPNCUSTOMIZE--telegram--VPNCUSTOMIZE--telegram--VPNCUSTOMIZE--telegram--VPNCUSTOMIZE--telegram----VPNCUSTOMIZE?ed=2048",
        "headers": {
          "Host": "seyyed.webdade.ip-ddns.com"
        }
      }
    },
    {
      "type": "vless",
      "tag": "vless-acfde351",
      "server": "www.visa.com",
      "server_port": 8080,
      "uuid": "0c04dd79-71ad-475e-9a22-8fe625afccbb",
      "flow": "",
      "tls": {
        "enabled": true,
        "server_name": "www.visa.com",
        "insecure": true
      },
      "transport": {
        "type": "ws",
        "path": "/telegram,ELiV2RAY-telegram,ELiV2RAY-telegram,ELiV2RAY-telegram,ELiV2RAY-telegram,ELiV2RAY-telegram,ELiV2RAY?ed=2560",
        "headers": {
          "Host": "seyyed.webdade.ip-ddns.com"
        }
      }
    },
    {
      "type": "vless",
      "tag": "vless-596fbf85",
      "server": "www.visa.com",
      "server_port": 8080,
      "uuid": "0c04dd79-71ad-475e-9a22-8fe625afccbb",
      "flow": "",
      "tls": {
        "enabled": true,
        "server_name": "www.visa.com",
        "insecure": true
      },
      "transport": {
        "type": "ws",
        "path": "/telegram,ELiV2RAY-telegram,ELiV2RAY-telegram,ELiV2RAY-telegram,ELiV2RAY-telegram,ELiV2RAY-telegram,ELiV2RAY?ed=2560",
        "headers": {
          "Host": "seyyed.webdade.ip-ddns.com"
        }
      }
    },
    {
      "type": "vless",
      "tag": "vless-e17d5fda",
      "server": "www.visa.com",
      "server_port": 8080,
      "uuid": "0c04dd79-71ad-475e-9a22-8fe625afccbb",
      "flow": "",
      "tls": {
        "enabled": true,
        "server_name": "www.visa.com",
        "insecure": true
      },
      "transport": {
        "type": "ws",
        "path": "/telegram,ELiV2RAY-telegram,ELiV2RAY-telegram,ELiV2RAY-telegram,ELiV2RAY-telegram,ELiV2RAY-telegram,ELiV2RAY?ed=2560",
        "headers": {
          "Host": "seyyed.webdade.ip-ddns.com"
        }
      }
    },
    {
      "type": "vless",
      "tag": "vless-0b4e0e13",
      "server": "zula.ir",
      "server_port": 8080,
      "uuid": "0c04dd79-71ad-475e-9a22-8fe625afccbb",
      "flow": "",
      "tls": {
        "enabled": true,
        "server_name": "zula.ir",
        "insecure": true
      },
      "transport": {
        "type": "ws",
        "path": "/telegram---VPNCUSTOMIZE--telegram--VPNCUSTOMIZE--telegram--VPNCUSTOMIZE--telegram--VPNCUSTOMIZE--telegram----VPNCUSTOMIZE?ed=2048",
        "headers": {
          "Host": "seyyed.webdade.ip-ddns.com"
        }
      }
    },
    {
      "type": "trojan",
      "tag": "trojan-d03f5255",
      "server": "18.238.109.28",
      "server_port": 443,
      "password": "0000000",
      "tls": {
        "enabled": true,
        "server_name": "www.lovelive-anime.jp",
        "alpn": [],
        "insecure": true
      },
      "transport": {}
    },
    {
      "type": "trojan",
      "tag": "trojan-93a53dd8",
      "server": "18.238.109.28",
      "server_port": 443,
      "password": "0000000",
      "tls": {
        "enabled": true,
        "server_name": "www.lovelive-anime.jp",
        "alpn": [],
        "insecure": true
      },
      "transport": {}
    },
    {
      "type": "trojan",
      "tag": "trojan-1c80afce",
      "server": "18.238.109.41",
      "server_port": 443,
      "password": "0000000",
      "tls": {
        "enabled": true,
        "server_name": "www.lovelive-anime.jp",
        "alpn": [],
        "insecure": true
      },
      "transport": {}
    },
    {
      "type": "trojan",
      "tag": "trojan-18d24d78",
      "server": "74.226.136.204",
      "server_port": 443,
      "password": "243eab52-9ac1-405c-887c-eb112c0985b8",
      "tls": {
        "enabled": true,
        "server_name": "hk03.trojanyyds.xyz",
        "alpn": [],
        "insecure": true
      },
      "transport": {}
    },
    {
      "type": "trojan",
      "tag": "trojan-db806aa3",
      "server": "model-fly.adder289.quest",
      "server_port": 443,
      "password": "3747000103274291200",
      "tls": {
        "enabled": true,
        "server_name": "model-fly.adder289.quest",
        "alpn": [],
        "insecure": true
      },
      "transport": {}
    },
    {
      "type": "trojan",
      "tag": "trojan-4c293a6d",
      "server": "oriented-pug.adder289.quest",
      "server_port": 443,
      "password": "3747000103274291200",
      "tls": {
        "enabled": true,
        "server_name": "oriented-pug.adder289.quest",
        "alpn": [],
        "insecure": true
      },
      "transport": {}
    },
    {
      "type": "trojan",
      "tag": "trojan-eaaf6c7b",
      "server": "destined-cub.treefrog761.one",
      "server_port": 443,
      "password": "3774827088566296576",
      "tls": {
        "enabled": true,
        "server_name": "destined-cub.treefrog761.one",
        "alpn": [],
        "insecure": true
      },
      "transport": {}
    },
    {
      "type": "trojan",
      "tag": "trojan-e177bcf9",
      "server": "www.tiktok.com.jp1.viefast.net",
      "server_port": 443,
      "password": "3bcd9e33-8377-4b32-af33-217158577ff3",
      "tls": {
        "enabled": true,
        "server_name": "kdlsupport.zendesk.com",
        "alpn": [],
        "insecure": true
      },
      "transport": {}
    },
    {
      "type": "trojan",
      "tag": "trojan-a992ccdd",
      "server": "www.tiktok.com.jp3.viefast.net",
      "server_port": 443,
      "password": "3bcd9e33-8377-4b32-af33-217158577ff3",
      "tls": {
        "enabled": true,
        "server_name": "kdlsupport.zendesk.com",
        "alpn": [],
        "insecure": true
      },
      "transport": {}
    },
    {
      "type": "trojan",
      "tag": "trojan-c55d2cc0",
      "server": "www.tiktok.com.jp3.viefast.net",
      "server_port": 443,
      "password": "3bcd9e33-8377-4b32-af33-217158577ff3",
      "tls": {
        "enabled": true,
        "server_name": "kdlsupport.zendesk.com",
        "alpn": [],
        "insecure": true
      },
      "transport": {}
    },
    {
      "type": "trojan",
      "tag": "trojan-d5bee926",
      "server": "104.251.227.182",
      "server_port": 443,
      "password": "43e5eeacbad3032bfe4c25a2f011b6b7",
      "tls": {
        "enabled": true,
        "server_name": "hezijiasuqi.com",
        "alpn": [],
        "insecure": true
      },
      "transport": {}
    },
    {
      "type": "trojan",
      "tag": "trojan-6fd5968b",
      "server": "tops-lobster.shiner427.skin",
      "server_port": 443,
      "password": "65086441068973800",
      "tls": {
        "enabled": true,
        "server_name": "tops-lobster.shiner427.skin",
        "alpn": [],
        "insecure": true
      },
      "transport": {}
    },
    {
      "type": "trojan",
      "tag": "trojan-6b1d7e9f",
      "server": "au.mjt000.com",
      "server_port": 443,
      "password": "6557bf4a-852b-4a69-ad35-d53293386a13",
      "tls": {
        "enabled": true,
        "server_name": "au.mjt000.com",
        "alpn": [],
        "insecure": true
      },
      "transport": {}
    },
    {
      "type": "trojan",
      "tag": "trojan-3756643b",
      "server": "it.mjt000.com",
      "server_port": 443,
      "password": "6557bf4a-852b-4a69-ad35-d53293386a13",
      "tls": {
        "enabled": true,
        "server_name": "it.mjt000.com",
        "alpn": [],
        "insecure": true
      },
      "transport": {}
    },
    {
      "type": "trojan",
      "tag": "trojan-df8a8d4f",
      "server": "uk.mjt000.com",
      "server_port": 443,
      "password": "6557bf4a-852b-4a69-ad35-d53293386a13",
      "tls": {
        "enabled": true,
        "server_name": "uk.mjt000.com",
        "alpn": [],
        "insecure": true
      },
      "transport": {}
    },
    {
      "type": "trojan",
      "tag": "trojan-683a29cf",
      "server": "usla.mjt000.com",
      "server_port": 443,
      "password": "6557bf4a-852b-4a69-ad35-d53293386a13",
      "tls": {
        "enabled": true,
        "server_name": "usla.mjt000.com",
        "alpn": [],
        "insecure": true
      },
      "transport": {}
    },
    {
      "type": "trojan",
      "tag": "trojan-82498354",
      "server": "104.16.159.5",
      "server_port": 443,
      "password": "984e400bf5d541b7b0815913fe0c432a",
      "tls": {
        "enabled": true,
        "server_name": "bangladeshipatri.com",
        "alpn": [],
        "insecure": true
      },
      "transport": {}
    },
    {
      "type": "trojan",
      "tag": "trojan-1899e9e3",
      "server": "108.165.152.55",
      "server_port": 2096,
      "password": "Aimer",
      "tls": {
        "enabled": true,
        "server_name": "ngepx.ambercc.filegear-sg.me",
        "alpn": [],
        "insecure": true
      },
      "transport": {}
    },
    {
      "type": "trojan",
      "tag": "trojan-3e01f3db",
      "server": "162.120.94.232",
      "server_port": 8443,
      "password": "Aimer",
      "tls": {
        "enabled": true,
        "server_name": "ngepy.ambercc.filegear-sg.me",
        "alpn": [],
        "insecure": true
      },
      "transport": {}
    },
    {
      "type": "trojan",
      "tag": "trojan-2bcee335",
      "server": "162.159.45.156",
      "server_port": 8443,
      "password": "Aimer",
      "tls": {
        "enabled": true,
        "server_name": "ngepz.ambercc.filegear-sg.me",
        "alpn": [
          "http/1.1"
        ],
        "insecure": true
      },
      "transport": {
        "type": "ws",
        "path": "/?ed=2560"
      }
    },
    {
      "type": "trojan",
      "tag": "trojan-25b3dee3",
      "server": "162.159.45.156",
      "server_port": 8443,
      "password": "Aimer",
      "tls": {
        "enabled": true,
        "server_name": "ngepz.ambercc.filegear-sg.me",
        "alpn": [
          "http/1.1"
        ],
        "insecure": true
      },
      "transport": {
        "type": "ws",
        "path": "/?ed=2560"
      }
    },
    {
      "type": "trojan",
      "tag": "trojan-1eb8b216",
      "server": "176.124.223.50",
      "server_port": 8443,
      "password": "Aimer",
      "tls": {
        "enabled": true,
        "server_name": "ngepx.ambercc.filegear-sg.me",
        "alpn": [],
        "insecure": true
      },
      "transport": {}
    },
    {
      "type": "trojan",
      "tag": "trojan-b654ad3f",
      "server": "178.159.43.246",
      "server_port": 8443,
      "password": "Aimer",
      "tls": {
        "enabled": true,
        "server_name": "agepq.ambercc.filegear-sg.me",
        "alpn": [],
        "insecure": true
      },
      "transport": {
        "type": "ws",
        "path": "/"
      }
    },
    {
      "type": "trojan",
      "tag": "trojan-3ecd6981",
      "server": "185.204.109.190",
      "server_port": 8443,
      "password": "Aimer",
      "tls": {
        "enabled": true,
        "server_name": "ngepo.ambercc.filegear-sg.me",
        "alpn": [],
        "insecure": true
      },
      "transport": {}
    },
    {
      "type": "trojan",
      "tag": "trojan-69561504",
      "server": "185.51.246.121",
      "server_port": 2053,
      "password": "Aimer",
      "tls": {
        "enabled": true,
        "server_name": "agepq.ambercc.filegear-sg.me",
        "alpn": [],
        "insecure": true
      },
      "transport": {
        "type": "ws",
        "path": "/"
      }
    },
    {
      "type": "trojan",
      "tag": "trojan-c9ed7635",
      "server": "210.99.204.14",
      "server_port": 10044,
      "password": "Aimer",
      "tls": {
        "enabled": true,
        "server_name": "ngepo.ambercc.filegear-sg.me",
        "alpn": [],
        "insecure": true
      },
      "transport": {}
    },
    {
      "type": "trojan",
      "tag": "trojan-941d2d86",
      "server": "216.24.57.186",
      "server_port": 443,
      "password": "Aimer",
      "tls": {
        "enabled": true,
        "server_name": "ngepx.ambercc.filegear-sg.me",
        "alpn": [],
        "insecure": true
      },
      "transport": {}
    },
    {
      "type": "trojan",
      "tag": "trojan-cb72fcfb",
      "server": "220.74.106.40",
      "server_port": 50000,
      "password": "Aimer",
      "tls": {
        "enabled": true,
        "server_name": "ngepy.ambercc.filegear-sg.me",
        "alpn": [],
        "insecure": true
      },
      "transport": {}
    },
    {
      "type": "trojan",
      "tag": "trojan-cb029561",
      "server": "27.50.49.166",
      "server_port": 8443,
      "password": "Aimer",
      "tls": {
        "enabled": true,
        "server_name": "acepo.ambercc.filegear-sg.me",
        "alpn": [],
        "insecure": true
      },
      "transport": {}
    },
    {
      "type": "trojan",
      "tag": "trojan-5fc7d7cf",
      "server": "3.132.116.250",
      "server_port": 443,
      "password": "Aimer",
      "tls": {
        "enabled": true,
        "server_name": "ngepy.ambercc.filegear-sg.me",
        "alpn": [],
        "insecure": true
      },
      "transport": {}
    },
    {
      "type": "trojan",
      "tag": "trojan-30193c19",
      "server": "45.67.215.217",
      "server_port": 2087,
      "password": "Aimer",
      "tls": {
        "enabled": true,
        "server_name": "ngepy.ambercc.filegear-sg.me",
        "alpn": [],
        "insecure": true
      },
      "transport": {}
    },
    {
      "type": "trojan",
      "tag": "trojan-1991af5f",
      "server": "59.1.59.225",
      "server_port": 50000,
      "password": "Aimer",
      "tls": {
        "enabled": true,
        "server_name": "ngepo.ambercc.filegear-sg.me",
        "alpn": [],
        "insecure": true
      },
      "transport": {}
    },
    {
      "type": "trojan",
      "tag": "trojan-9fe61287",
      "server": "66.81.247.88",
      "server_port": 2083,
      "password": "Aimer",
      "tls": {
        "enabled": true,
        "server_name": "ameqo.esslh.filegear-sg.me",
        "alpn": [],
        "insecure": true
      },
      "transport": {}
    },
    {
      "type": "trojan",
      "tag": "trojan-bda8a2b3",
      "server": "158.247.240.85",
      "server_port": 443,
      "password": "Bw5Mz7QkVp",
      "tls": {
        "enabled": true,
        "server_name": "z-v2-082561.kailib.com",
        "alpn": [],
        "insecure": true
      },
      "transport": {}
    },
    {
      "type": "trojan",
      "tag": "trojan-b4358c28",
      "server": "z-v2-080448.kailib.com",
      "server_port": 443,
      "password": "Bw5Mz7QkVp",
      "tls": {
        "enabled": true,
        "server_name": "z-v2-080448.kailib.com",
        "alpn": [],
        "insecure": true
      },
      "transport": {}
    },
    {
      "type": "trojan",
      "tag": "trojan-a03c0689",
      "server": "z-v2-080450.kailib.com",
      "server_port": 443,
      "password": "Bw5Mz7QkVp",
      "tls": {
        "enabled": true,
        "server_name": "z-v2-080450.kailib.com",
        "alpn": [],
        "insecure": true
      },
      "transport": {}
    },
    {
      "type": "trojan",
      "tag": "trojan-f9af0c86",
      "server": "z-v2-080466.kailib.com",
      "server_port": 443,
      "password": "Bw5Mz7QkVp",
      "tls": {
        "enabled": true,
        "server_name": "z-v2-080466.kailib.com",
        "alpn": [],
        "insecure": true
      },
      "transport": {}
    },
    {
      "type": "trojan",
      "tag": "trojan-5c71dcb3",
      "server": "z-v2-080487.kailib.com",
      "server_port": 443,
      "password": "Bw5Mz7QkVp",
      "tls": {
        "enabled": true,
        "server_name": "z-v2-080487.kailib.com",
        "alpn": [],
        "insecure": true
      },
      "transport": {}
    },
    {
      "type": "trojan",
      "tag": "trojan-b7e3e5ba",
      "server": "z-v2-080503.kailib.com",
      "server_port": 443,
      "password": "Bw5Mz7QkVp",
      "tls": {
        "enabled": true,
        "server_name": "z-v2-080503.kailib.com",
        "alpn": [],
        "insecure": true
      },
      "transport": {}
    },
    {
      "type": "trojan",
      "tag": "trojan-08ad8740",
      "server": "z-v2-080505.kailib.com",
      "server_port": 443,
      "password": "Bw5Mz7QkVp",
      "tls": {
        "enabled": true,
        "server_name": "z-v2-080505.kailib.com",
        "alpn": [],
        "insecure": true
      },
      "transport": {}
    },
    {
      "type": "trojan",
      "tag": "trojan-b2683d17",
      "server": "z-v2-080515.kailib.com",
      "server_port": 443,
      "password": "Bw5Mz7QkVp",
      "tls": {
        "enabled": true,
        "server_name": "z-v2-080515.kailib.com",
        "alpn": [],
        "insecure": true
      },
      "transport": {}
    },
    {
      "type": "trojan",
      "tag": "trojan-018b975c",
      "server": "z-v2-080532.kailib.com",
      "server_port": 443,
      "password": "Bw5Mz7QkVp",
      "tls": {
        "enabled": true,
        "server_name": "z-v2-080532.kailib.com",
        "alpn": [],
        "insecure": true
      },
      "transport": {}
    },
    {
      "type": "trojan",
      "tag": "trojan-458a7d03",
      "server": "z-v2-080537.kailib.com",
      "server_port": 443,
      "password": "Bw5Mz7QkVp",
      "tls": {
        "enabled": true,
        "server_name": "z-v2-080537.kailib.com",
        "alpn": [],
        "insecure": true
      },
      "transport": {}
    },
    {
      "type": "trojan",
      "tag": "trojan-dd146289",
      "server": "z-v2-080560.kailib.com",
      "server_port": 443,
      "password": "Bw5Mz7QkVp",
      "tls": {
        "enabled": true,
        "server_name": "z-v2-080560.kailib.com",
        "alpn": [],
        "insecure": true
      },
      "transport": {}
    },
    {
      "type": "trojan",
      "tag": "trojan-6a490e74",
      "server": "z-v2-082492.kailib.com",
      "server_port": 443,
      "password": "Bw5Mz7QkVp",
      "tls": {
        "enabled": true,
        "server_name": "z-v2-082492.kailib.com",
        "alpn": [],
        "insecure": true
      },
      "transport": {}
    },
    {
      "type": "trojan",
      "tag": "trojan-bb3e4825",
      "server": "z-v2-082496.kailib.com",
      "server_port": 443,
      "password": "Bw5Mz7QkVp",
      "tls": {
        "enabled": true,
        "server_name": "z-v2-082496.kailib.com",
        "alpn": [],
        "insecure": true
      },
      "transport": {}
    },
    {
      "type": "trojan",
      "tag": "trojan-03977796",
      "server": "z-v2-082496.kailib.com",
      "server_port": 443,
      "password": "Bw5Mz7QkVp",
      "tls": {
        "enabled": true,
        "server_name": "z-v2-082496.kailib.com",
        "alpn": [],
        "insecure": true
      },
      "transport": {}
    },
    {
      "type": "trojan",
      "tag": "trojan-d65f433b",
      "server": "z-v2-082509.kailib.com",
      "server_port": 443,
      "password": "Bw5Mz7QkVp",
      "tls": {
        "enabled": true,
        "server_name": "z-v2-082509.kailib.com",
        "alpn": [],
        "insecure": true
      },
      "transport": {}
    },
    {
      "type": "trojan",
      "tag": "trojan-44511431",
      "server": "z-v2-082533.kailib.com",
      "server_port": 443,
      "password": "Bw5Mz7QkVp",
      "tls": {
        "enabled": true,
        "server_name": "z-v2-082533.kailib.com",
        "alpn": [],
        "insecure": true
      },
      "transport": {}
    },
    {
      "type": "trojan",
      "tag": "trojan-89719fdf",
      "server": "z-v2-082548.kailib.com",
      "server_port": 443,
      "password": "Bw5Mz7QkVp",
      "tls": {
        "enabled": true,
        "server_name": "z-v2-082548.kailib.com",
        "alpn": [],
        "insecure": true
      },
      "transport": {}
    },
    {
      "type": "trojan",
      "tag": "trojan-6ee7c0cf",
      "server": "z-v2-082550.kailib.com",
      "server_port": 443,
      "password": "Bw5Mz7QkVp",
      "tls": {
        "enabled": true,
        "server_name": "z-v2-082550.kailib.com",
        "alpn": [],
        "insecure": true
      },
      "transport": {}
    },
    {
      "type": "trojan",
      "tag": "trojan-1c3881c7",
      "server": "z-v2-082554.kailib.com",
      "server_port": 443,
      "password": "Bw5Mz7QkVp",
      "tls": {
        "enabled": true,
        "server_name": "z-v2-082554.kailib.com",
        "alpn": [],
        "insecure": true
      },
      "transport": {}
    },
    {
      "type": "trojan",
      "tag": "trojan-b95ad2a1",
      "server": "z-v2-082561.kailib.com",
      "server_port": 443,
      "password": "Bw5Mz7QkVp",
      "tls": {
        "enabled": true,
        "server_name": "z-v2-082561.kailib.com",
        "alpn": [],
        "insecure": true
      },
      "transport": {}
    },
    {
      "type": "trojan",
      "tag": "trojan-badbd5db",
      "server": "z-v2-082569.kailib.com",
      "server_port": 443,
      "password": "Bw5Mz7QkVp",
      "tls": {
        "enabled": true,
        "server_name": "z-v2-082569.kailib.com",
        "alpn": [],
        "insecure": true
      },
      "transport": {}
    },
    {
      "type": "trojan",
      "tag": "trojan-d08f85fb",
      "server": "z-v2-082689.kailib.com",
      "server_port": 443,
      "password": "Bw5Mz7QkVp",
      "tls": {
        "enabled": true,
        "server_name": "z-v2-082689.kailib.com",
        "alpn": [],
        "insecure": true
      },
      "transport": {}
    },
    {
      "type": "trojan",
      "tag": "trojan-da109940",
      "server": "z-v2-082691.kailib.com",
      "server_port": 443,
      "password": "Bw5Mz7QkVp",
      "tls": {
        "enabled": true,
        "server_name": "z-v2-082691.kailib.com",
        "alpn": [],
        "insecure": true
      },
      "transport": {}
    },
    {
      "type": "vmess",
      "tag": "vmess-9f769a26",
      "server": "38.14.107.228",
      "server_port": 38003,
      "uuid": "418048af-a293-4b99-9b0c-98ca3580dd24",
      "security": "auto",
      "alter_id": 64,
      "transport": {
        "type": "ws",
        "path": "/path/181721272114",
        "headers": {
          "Host": "www.23179753.xyz"
        }
      },
      "tls": {
        "enabled": true,
        "insecure": true,
        "server_name": ""
      }
    },
    {
      "type": "vmess",
      "tag": "vmess-d327756c",
      "server": "38.174.190.75",
      "server_port": 38007,
      "uuid": "418048af-a293-4b99-9b0c-98ca3580dd24",
      "security": "auto",
      "alter_id": 64,
      "transport": {
        "type": "ws",
        "path": "/path/251724052818",
        "headers": {
          "Host": ""
        }
      },
      "tls": {
        "enabled": true,
        "insecure": true,
        "server_name": ""
      }
    },
    {
      "type": "vmess",
      "tag": "vmess-c7dfd907",
      "server": "www.visa.com.tw",
      "server_port": 443,
      "uuid": "301fad67-1288-47a9-b3ca-22b823e4e789",
      "security": "auto",
      "alter_id": 0,
      "transport": {
        "type": "ws",
        "path": "/vmess-argo?ed=2048",
        "headers": {
          "Host": "s2.2go.us.kg"
        }
      },
      "tls": {
        "enabled": true,
        "insecure": true,
        "server_name": ""
      }
    },
    {
      "type": "vmess",
      "tag": "vmess-1afcf2b1",
      "server": "101.99.91.234",
      "server_port": 36700,
      "uuid": "127ff43c-1851-4b2d-ba8c-6afba21ec04d",
      "security": "auto",
      "alter_id": 0,
      "transport": {},
      "tls": {
        "enabled": false,
        "insecure": true,
        "server_name": "101.99.91.234"
      }
    },
    {
      "type": "vmess",
      "tag": "vmess-3c1f5707",
      "server": "101.99.91.234",
      "server_port": 36700,
      "uuid": "127ff43c-1851-4b2d-ba8c-6afba21ec04d",
      "security": "auto",
      "alter_id": 0,
      "transport": {},
      "tls": {
        "enabled": false,
        "insecure": true,
        "server_name": "101.99.91.234"
      }
    },
    {
      "type": "vmess",
      "tag": "vmess-c5736719",
      "server": "46.250.253.232",
      "server_port": 46617,
      "uuid": "55b88b14-0ff3-4f25-8983-e73d1f9f3a0a",
      "security": "auto",
      "alter_id": 0,
      "transport": {},
      "tls": {
        "enabled": false,
        "insecure": true,
        "server_name": "46.250.253.232"
      }
    },
    {
      "type": "vmess",
      "tag": "vmess-a1618eaf",
      "server": "62.146.233.159",
      "server_port": 43763,
      "uuid": "1ddf3ade-5b8c-420c-84f6-f96979ec3080",
      "security": "auto",
      "alter_id": 0,
      "transport": {},
      "tls": {
        "enabled": false,
        "insecure": true,
        "server_name": "62.146.233.159"
      }
    },
    {
      "type": "vmess",
      "tag": "vmess-c1dbd78a",
      "server": "15.204.249.0",
      "server_port": 48160,
      "uuid": "5b113c12-4dd4-4bb5-9c01-cff092b559e3",
      "security": "auto",
      "alter_id": 0,
      "transport": {},
      "tls": {
        "enabled": false,
        "insecure": true,
        "server_name": "15.204.249.0"
      }
    },
    {
      "type": "vmess",
      "tag": "vmess-8909e1da",
      "server": "193.108.117.143",
      "server_port": 24164,
      "uuid": "aa3c5c18-6578-4de3-b890-2fd25c3a8f35",
      "security": "auto",
      "alter_id": 0,
      "transport": {},
      "tls": {
        "enabled": false,
        "insecure": true,
        "server_name": "193.108.117.143"
      }
    },
    {
      "type": "vmess",
      "tag": "vmess-2f01dd29",
      "server": "38.109.228.113",
      "server_port": 21809,
      "uuid": "a6179475-489c-4bcc-b05c-481386295b93",
      "security": "auto",
      "alter_id": 0,
      "transport": {},
      "tls": {
        "enabled": false,
        "insecure": true,
        "server_name": "38.109.228.113"
      }
    },
    {
      "type": "vmess",
      "tag": "vmess-b4de9c47",
      "server": "103.67.79.157",
      "server_port": 45365,
      "uuid": "7d2a4e66-152c-49f5-9ff5-c19a836e8c89",
      "security": "auto",
      "alter_id": 0,
      "transport": {},
      "tls": {
        "enabled": false,
        "insecure": true,
        "server_name": "103.67.79.157"
      }
    },
    {
      "type": "vmess",
      "tag": "vmess-5e9b34d3",
      "server": "109.123.232.74",
      "server_port": 59032,
      "uuid": "96ab7e1f-bf0d-45cd-8ebc-c8be2f8d43cd",
      "security": "auto",
      "alter_id": 0,
      "transport": {},
      "tls": {
        "enabled": false,
        "insecure": true,
        "server_name": "109.123.232.74"
      }
    },
    {
      "type": "vmess",
      "tag": "vmess-d339ac90",
      "server": "154.26.137.42",
      "server_port": 44104,
      "uuid": "e9933a4c-e56e-458c-bcf4-9cb3875bba55",
      "security": "auto",
      "alter_id": 0,
      "transport": {},
      "tls": {
        "enabled": false,
        "insecure": true,
        "server_name": "154.26.137.42"
      }
    },
    {
      "type": "vmess",
      "tag": "vmess-5a87bcd1",
      "server": "62.146.232.159",
      "server_port": 14372,
      "uuid": "ed1d7ea8-bf40-4a4a-8eac-8e57798ba6f7",
      "security": "auto",
      "alter_id": 0,
      "transport": {},
      "tls": {
        "enabled": false,
        "insecure": true,
        "server_name": "62.146.232.159"
      }
    },
    {
      "type": "vmess",
      "tag": "vmess-7c42f89f",
      "server": "62.146.233.53",
      "server_port": 50678,
      "uuid": "5d1ec6e7-fd58-4e85-91c5-6335a86d2775",
      "security": "auto",
      "alter_id": 0,
      "transport": {},
      "tls": {
        "enabled": false,
        "insecure": true,
        "server_name": "62.146.233.53"
      }
    },
    {
      "type": "vmess",
      "tag": "vmess-43638b48",
      "server": "103.67.79.157",
      "server_port": 45365,
      "uuid": "7d2a4e66-152c-49f5-9ff5-c19a836e8c89",
      "security": "auto",
      "alter_id": 0,
      "transport": {},
      "tls": {
        "enabled": false,
        "insecure": true,
        "server_name": "103.67.79.157"
      }
    },
    {
      "type": "vmess",
      "tag": "vmess-594c9990",
      "server": "20.213.20.185",
      "server_port": 17718,
      "uuid": "c206e022-34c6-4fe3-a232-b9c07ba3165d",
      "security": "auto",
      "alter_id": 0,
      "transport": {},
      "tls": {
        "enabled": false,
        "insecure": true,
        "server_name": "20.213.20.185"
      }
    },
    {
      "type": "vmess",
      "tag": "vmess-14851bde",
      "server": "4.240.73.55",
      "server_port": 14118,
      "uuid": "d513bfb2-b7c2-4dc6-a3f9-55145f198705",
      "security": "auto",
      "alter_id": 0,
      "transport": {},
      "tls": {
        "enabled": false,
        "insecure": true,
        "server_name": "4.240.73.55"
      }
    },
    {
      "type": "vmess",
      "tag": "vmess-9fa11333",
      "server": "94.136.184.156",
      "server_port": 38872,
      "uuid": "220732cc-9e43-4453-83f1-c9435be25b5b",
      "security": "auto",
      "alter_id": 0,
      "transport": {},
      "tls": {
        "enabled": false,
        "insecure": true,
        "server_name": "94.136.184.156"
      }
    },
    {
      "type": "vmess",
      "tag": "vmess-5827f0b5",
      "server": "149.7.16.149",
      "server_port": 37101,
      "uuid": "fb3fc243-4698-49c4-8c44-0415f68a4d25",
      "security": "auto",
      "alter_id": 0,
      "transport": {},
      "tls": {
        "enabled": false,
        "insecure": true,
        "server_name": "149.7.16.149"
      }
    },
    {
      "type": "vmess",
      "tag": "vmess-ad2ab857",
      "server": "15.204.248.92",
      "server_port": 30562,
      "uuid": "82466715-6a58-4046-a363-a0d18e5b2ab4",
      "security": "auto",
      "alter_id": 0,
      "transport": {},
      "tls": {
        "enabled": false,
        "insecure": true,
        "server_name": "15.204.248.92"
      }
    },
    {
      "type": "vmess",
      "tag": "vmess-daff147a",
      "server": "20.213.20.185",
      "server_port": 17718,
      "uuid": "c206e022-34c6-4fe3-a232-b9c07ba3165d",
      "security": "auto",
      "alter_id": 0,
      "transport": {},
      "tls": {
        "enabled": false,
        "insecure": true,
        "server_name": "20.213.20.185"
      }
    },
    {
      "type": "vmess",
      "tag": "vmess-131eb9bd",
      "server": "172.188.27.157",
      "server_port": 45732,
      "uuid": "c0068718-4d5e-4e65-8e5f-809820339b1f",
      "security": "auto",
      "alter_id": 0,
      "transport": {},
      "tls": {
        "enabled": false,
        "insecure": true,
        "server_name": "172.188.27.157"
      }
    },
    {
      "type": "vmess",
      "tag": "vmess-a492dbd0",
      "server": "38.111.114.153",
      "server_port": 14812,
      "uuid": "0146fc40-5962-4e9a-b36a-2b606d001467",
      "security": "auto",
      "alter_id": 0,
      "transport": {},
      "tls": {
        "enabled": false,
        "insecure": true,
        "server_name": "38.111.114.153"
      }
    },
    {
      "type": "vmess",
      "tag": "vmess-a96b8e57",
      "server": "62.146.232.156",
      "server_port": 33281,
      "uuid": "24eda0ea-acf0-4538-a001-f746a480237a",
      "security": "auto",
      "alter_id": 0,
      "transport": {},
      "tls": {
        "enabled": false,
        "insecure": true,
        "server_name": "62.146.232.156"
      }
    },
    {
      "type": "vmess",
      "tag": "vmess-f0d1ae9d",
      "server": "38.114.120.12",
      "server_port": 47567,
      "uuid": "cda5dfaa-99e8-42d6-9f0b-6ef30f76e92c",
      "security": "auto",
      "alter_id": 0,
      "transport": {},
      "tls": {
        "enabled": false,
        "insecure": true,
        "server_name": "38.114.120.12"
      }
    },
    {
      "type": "vmess",
      "tag": "vmess-cb26382d",
      "server": "193.108.118.136",
      "server_port": 15713,
      "uuid": "f74e277e-84b3-46a2-8abd-2777fa5e4af9",
      "security": "auto",
      "alter_id": 0,
      "transport": {},
      "tls": {
        "enabled": false,
        "insecure": true,
        "server_name": "193.108.118.136"
      }
    },
    {
      "type": "vmess",
      "tag": "vmess-867e887c",
      "server": "4.240.73.55",
      "server_port": 14118,
      "uuid": "d513bfb2-b7c2-4dc6-a3f9-55145f198705",
      "security": "auto",
      "alter_id": 0,
      "transport": {},
      "tls": {
        "enabled": false,
        "insecure": true,
        "server_name": "4.240.73.55"
      }
    },
    {
      "type": "vmess",
      "tag": "vmess-2934f66f",
      "server": "109.123.232.74",
      "server_port": 59032,
      "uuid": "96ab7e1f-bf0d-45cd-8ebc-c8be2f8d43cd",
      "security": "auto",
      "alter_id": 0,
      "transport": {},
      "tls": {
        "enabled": false,
        "insecure": true,
        "server_name": "109.123.232.74"
      }
    },
    {
      "type": "vmess",
      "tag": "vmess-567cf0cd",
      "server": "23.158.56.21",
      "server_port": 48961,
      "uuid": "6eef3448-bbc0-4933-894a-72b3e8786109",
      "security": "auto",
      "alter_id": 0,
      "transport": {},
      "tls": {
        "enabled": false,
        "insecure": true,
        "server_name": ""
      }
    },
    {
      "type": "vmess",
      "tag": "vmess-47644e9d",
      "server": "142.93.68.147",
      "server_port": 8881,
      "uuid": "db5afae4-ac23-41a6-8378-f307a9a47436",
      "security": "auto",
      "alter_id": 0,
      "transport": {},
      "tls": {
        "enabled": false,
        "insecure": true,
        "server_name": ""
      }
    },
    {
      "type": "vmess",
      "tag": "vmess-88231101",
      "server": "101.99.91.234",
      "server_port": 36700,
      "uuid": "127ff43c-1851-4b2d-ba8c-6afba21ec04d",
      "security": "auto",
      "alter_id": 0,
      "transport": {},
      "tls": {
        "enabled": false,
        "insecure": true,
        "server_name": "101.99.91.234"
      }
    },
    {
      "type": "vmess",
      "tag": "vmess-1f3082ce",
      "server": "193.108.117.143",
      "server_port": 24164,
      "uuid": "aa3c5c18-6578-4de3-b890-2fd25c3a8f35",
      "security": "auto",
      "alter_id": 0,
      "transport": {},
      "tls": {
        "enabled": false,
        "insecure": true,
        "server_name": "193.108.117.143"
      }
    },
    {
      "type": "vmess",
      "tag": "vmess-d3644196",
      "server": "101.99.91.234",
      "server_port": 36700,
      "uuid": "127ff43c-1851-4b2d-ba8c-6afba21ec04d",
      "security": "auto",
      "alter_id": 0,
      "transport": {},
      "tls": {
        "enabled": false,
        "insecure": true,
        "server_name": ""
      }
    },
    {
      "type": "vmess",
      "tag": "vmess-22e7defb",
      "server": "103.67.79.157",
      "server_port": 45365,
      "uuid": "7d2a4e66-152c-49f5-9ff5-c19a836e8c89",
      "security": "auto",
      "alter_id": 0,
      "transport": {},
      "tls": {
        "enabled": false,
        "insecure": true,
        "server_name": ""
      }
    },
    {
      "type": "vmess",
      "tag": "vmess-b6982826",
      "server": "142.4.104.33",
      "server_port": 52143,
      "uuid": "418048af-a293-4b99-9b0c-98ca3580dd24",
      "security": "auto",
      "alter_id": 0,
      "transport": {},
      "tls": {
        "enabled": false,
        "insecure": true,
        "server_name": ""
      }
    },
    {
      "type": "vmess",
      "tag": "vmess-d3e94601",
      "server": "172.188.27.157",
      "server_port": 45732,
      "uuid": "c0068718-4d5e-4e65-8e5f-809820339b1f",
      "security": "auto",
      "alter_id": 0,
      "transport": {},
      "tls": {
        "enabled": false,
        "insecure": true,
        "server_name": ""
      }
    },
    {
      "type": "vmess",
      "tag": "vmess-adc3a4bb",
      "server": "209.97.176.198",
      "server_port": 8081,
      "uuid": "3873beec-44c6-45be-8900-d184a1d0ee8f",
      "security": "auto",
      "alter_id": 0,
      "transport": {},
      "tls": {
        "enabled": false,
        "insecure": true,
        "server_name": "209.97.176.198"
      }
    },
    {
      "type": "vmess",
      "tag": "vmess-8ad6af4c",
      "server": "20.205.176.167",
      "server_port": 54550,
      "uuid": "e696df27-62cc-4ca7-9a39-007c93cdaa46",
      "security": "auto",
      "alter_id": 0,
      "transport": {},
      "tls": {
        "enabled": false,
        "insecure": true,
        "server_name": ""
      }
    },
    {
      "type": "vmess",
      "tag": "vmess-29ce0955",
      "server": "31.58.142.221",
      "server_port": 8967,
      "uuid": "7d29f1ca-647b-4b4e-b9c8-6beab7133535",
      "security": "auto",
      "alter_id": 0,
      "transport": {
        "type": "ws",
        "path": "/BONRyKGhDE",
        "headers": {
          "Host": "neo.nicme.me"
        }
      },
      "tls": {
        "enabled": true,
        "insecure": true,
        "server_name": "neo.nicme.me"
      }
    },
    {
      "type": "vmess",
      "tag": "vmess-36658fda",
      "server": "79.127.229.54",
      "server_port": 18000,
      "uuid": "fa1897db-1925-4c86-a495-939a959af900",
      "security": "auto",
      "alter_id": 0,
      "transport": {},
      "tls": {
        "enabled": false,
        "insecure": true,
        "server_name": ""
      }
    },
    {
      "type": "vmess",
      "tag": "vmess-1d406b88",
      "server": "88.198.172.25",
      "server_port": 15145,
      "uuid": "e7eb472e-dc83-49d5-be5e-82a79a2124ee",
      "security": "auto",
      "alter_id": 0,
      "transport": {},
      "tls": {
        "enabled": false,
        "insecure": true,
        "server_name": ""
      }
    },
    {
      "type": "vmess",
      "tag": "vmess-01b3591b",
      "server": "95.216.170.50",
      "server_port": 58524,
      "uuid": "0797540d-3148-483a-b031-8b99af449dc7",
      "security": "auto",
      "alter_id": 0,
      "transport": {},
      "tls": {
        "enabled": false,
        "insecure": true,
        "server_name": ""
      }
    },
    {
      "type": "vmess",
      "tag": "vmess-8e34a5b7",
      "server": "45.32.210.214",
      "server_port": 8881,
      "uuid": "db5afae4-ac23-41a6-8378-f307a9a47436",
      "security": "auto",
      "alter_id": 0,
      "transport": {},
      "tls": {
        "enabled": false,
        "insecure": true,
        "server_name": ""
      }
    },
    {
      "type": "vmess",
      "tag": "vmess-75777faf",
      "server": "51.77.20.132",
      "server_port": 443,
      "uuid": "03fcc618-b93d-6796-6aed-8a38c975d581",
      "security": "auto",
      "alter_id": 0,
      "transport": {
        "type": "ws",
        "path": "/linkvws",
        "headers": {
          "Host": "a.baradiha.com"
        }
      },
      "tls": {
        "enabled": true,
        "insecure": true,
        "server_name": ""
      }
    },
    {
      "type": "vmess",
      "tag": "vmess-96dbe91d",
      "server": "57.129.24.142",
      "server_port": 443,
      "uuid": "03fcc618-b93d-6796-6aed-8a38c975d581",
      "security": "auto",
      "alter_id": 0,
      "transport": {
        "type": "ws",
        "path": "/linkvws",
        "headers": {
          "Host": "harriscity.com"
        }
      },
      "tls": {
        "enabled": true,
        "insecure": true,
        "server_name": ""
      }
    },
    {
      "type": "vmess",
      "tag": "vmess-fd33b1b5",
      "server": "66.42.85.70",
      "server_port": 8881,
      "uuid": "db5afae4-ac23-41a6-8378-f307a9a47436",
      "security": "auto",
      "alter_id": 0,
      "transport": {},
      "tls": {
        "enabled": false,
        "insecure": true,
        "server_name": ""
      }
    },
    {
      "type": "vmess",
      "tag": "vmess-eed3b549",
      "server": "81.28.12.12",
      "server_port": 443,
      "uuid": "800e5660-e7f3-11ef-b433-205c6d5f5d78",
      "security": "auto",
      "alter_id": 0,
      "transport": {
        "type": "ws",
        "path": "/l3ifpwc2",
        "headers": {
          "Host": "eu-fgfshety.maxima.us.kg"
        }
      },
      "tls": {
        "enabled": true,
        "insecure": true,
        "server_name": "gcore.lu"
      }
    },
    {
      "type": "vmess",
      "tag": "vmess-bf404906",
      "server": "81.28.12.12",
      "server_port": 443,
      "uuid": "9dad7de0-e7f3-11ef-b837-205c6d5f5d78",
      "security": "auto",
      "alter_id": 0,
      "transport": {
        "type": "ws",
        "path": "/i9n8uchm",
        "headers": {
          "Host": "sg-195xfgf.maxima.us.kg"
        }
      },
      "tls": {
        "enabled": true,
        "insecure": true,
        "server_name": "gcore.lu"
      }
    },
    {
      "type": "vmess",
      "tag": "vmess-75303389",
      "server": "81.28.12.12",
      "server_port": 443,
      "uuid": "46527530-e7f3-11ef-b131-205c6d5f5d78",
      "security": "auto",
      "alter_id": 0,
      "transport": {
        "type": "ws",
        "path": "/4fmplb6g",
        "headers": {
          "Host": "us-3696fdsbg.maxima.us.kg"
        }
      },
      "tls": {
        "enabled": true,
        "insecure": true,
        "server_name": "gcore.lu"
      }
    },
    {
      "type": "vmess",
      "tag": "vmess-e82f6202",
      "server": "81.28.12.12",
      "server_port": 443,
      "uuid": "63a74780-e7f3-11ef-b431-205c6d5f5d78",
      "security": "auto",
      "alter_id": 0,
      "transport": {
        "type": "ws",
        "path": "/4yuvewgn",
        "headers": {
          "Host": "us-799jfghfh.maxima.us.kg"
        }
      },
      "tls": {
        "enabled": true,
        "insecure": true,
        "server_name": "gcore.lu"
      }
    },
    {
      "type": "vmess",
      "tag": "vmess-13cc7caa",
      "server": "88.198.172.25",
      "server_port": 15145,
      "uuid": "e7eb472e-dc83-49d5-be5e-82a79a2124ee",
      "security": "auto",
      "alter_id": 0,
      "transport": {},
      "tls": {
        "enabled": false,
        "insecure": true,
        "server_name": ""
      }
    },
    {
      "type": "vmess",
      "tag": "vmess-b680d079",
      "server": "91.107.247.219",
      "server_port": 27660,
      "uuid": "25829065-865f-49bb-995b-46c1e03ae71d",
      "security": "auto",
      "alter_id": 0,
      "transport": {},
      "tls": {
        "enabled": false,
        "insecure": true,
        "server_name": ""
      }
    },
    {
      "type": "vmess",
      "tag": "vmess-11155bf3",
      "server": "95.164.4.88",
      "server_port": 80,
      "uuid": "c04c3b34-70fd-4fec-963e-c12d09f36bef",
      "security": "auto",
      "alter_id": 0,
      "transport": {
        "type": "ws",
        "path": "/vmess/",
        "headers": {
          "Host": "pq-brazil1.09vpn.com"
        }
      },
      "tls": {
        "enabled": false,
        "insecure": true,
        "server_name": ""
      }
    },
    {
      "type": "vmess",
      "tag": "vmess-43e2e301",
      "server": "95.216.170.50",
      "server_port": 42255,
      "uuid": "aa053b7c-c766-41e0-b379-be7c6e965900",
      "security": "auto",
      "alter_id": 0,
      "transport": {},
      "tls": {
        "enabled": false,
        "insecure": true,
        "server_name": ""
      }
    },
    {
      "type": "vmess",
      "tag": "vmess-9a3a33d1",
      "server": "103.67.79.157",
      "server_port": 45365,
      "uuid": "7d2a4e66-152c-49f5-9ff5-c19a836e8c89",
      "security": "auto",
      "alter_id": 0,
      "transport": {},
      "tls": {
        "enabled": false,
        "insecure": true,
        "server_name": ""
      }
    },
    {
      "type": "vmess",
      "tag": "vmess-ab1961df",
      "server": "104.19.150.10",
      "server_port": 2095,
      "uuid": "94f332b0-c5d3-4531-a1d6-6e6358cc6c72",
      "security": "auto",
      "alter_id": 0,
      "transport": {},
      "tls": {
        "enabled": false,
        "insecure": true,
        "server_name": ""
      }
    },
    {
      "type": "vmess",
      "tag": "vmess-99c9d086",
      "server": "104.19.150.10",
      "server_port": 2095,
      "uuid": "94f332b0-c5d3-4531-a1d6-6e6358cc6c72",
      "security": "auto",
      "alter_id": 0,
      "transport": {},
      "tls": {
        "enabled": false,
        "insecure": true,
        "server_name": ""
      }
    },
    {
      "type": "vmess",
      "tag": "vmess-3b8b342c",
      "server": "104.252.127.152",
      "server_port": 32288,
      "uuid": "84c77664-1156-473f-a1e3-876623fb840d",
      "security": "auto",
      "alter_id": 0,
      "transport": {},
      "tls": {
        "enabled": false,
        "insecure": true,
        "server_name": ""
      }
    },
    {
      "type": "vmess",
      "tag": "vmess-26d794a5",
      "server": "142.4.108.147",
      "server_port": 38007,
      "uuid": "418048af-a293-4b99-9b0c-98ca3580dd24",
      "security": "auto",
      "alter_id": 64,
      "transport": {
        "type": "ws",
        "path": "/path/181721272114",
        "headers": {
          "Host": ""
        }
      },
      "tls": {
        "enabled": true,
        "insecure": true,
        "server_name": ""
      }
    },
    {
      "type": "vmess",
      "tag": "vmess-2413b649",
      "server": "142.4.108.141",
      "server_port": 38007,
      "uuid": "418048af-a293-4b99-9b0c-98ca3580dd24",
      "security": "auto",
      "alter_id": 64,
      "transport": {
        "type": "ws",
        "path": "/path/1723457615032",
        "headers": {
          "Host": "www.66827194.xyz"
        }
      },
      "tls": {
        "enabled": true,
        "insecure": true,
        "server_name": "www.66827194.xyz"
      }
    },
    {
      "type": "vmess",
      "tag": "vmess-2d76c876",
      "server": "144.202.27.128",
      "server_port": 8881,
      "uuid": "db5afae4-ac23-41a6-8378-f307a9a47436",
      "security": "auto",
      "alter_id": 0,
      "transport": {},
      "tls": {
        "enabled": false,
        "insecure": true,
        "server_name": ""
      }
    },
    {
      "type": "vmess",
      "tag": "vmess-625b8630",
      "server": "146.19.168.161",
      "server_port": 443,
      "uuid": "3f638f34-8dba-4186-bc43-2716a7ddd4be",
      "security": "auto",
      "alter_id": 0,
      "transport": {
        "type": "ws",
        "path": "/link",
        "headers": {
          "Host": "az05.beyondy.cfd"
        }
      },
      "tls": {
        "enabled": true,
        "insecure": true,
        "server_name": "az05.beyondy.cfd"
      }
    },
    {
      "type": "vmess",
      "tag": "vmess-3f136e86",
      "server": "151.101.0.155",
      "server_port": 80,
      "uuid": "ca387597-d79e-48c2-89a7-e2dc66a88a70",
      "security": "auto",
      "alter_id": 0,
      "transport": {
        "type": "ws",
        "path": "/racevpn",
        "headers": {
          "Host": "telegram-isvvpn.ir"
        }
      },
      "tls": {
        "enabled": false,
        "insecure": true,
        "server_name": ""
      }
    },
    {
      "type": "vmess",
      "tag": "vmess-40c58600",
      "server": "20.213.20.185",
      "server_port": 17718,
      "uuid": "c206e022-34c6-4fe3-a232-b9c07ba3165d",
      "security": "auto",
      "alter_id": 0,
      "transport": {},
      "tls": {
        "enabled": false,
        "insecure": true,
        "server_name": ""
      }
    },
    {
      "type": "vmess",
      "tag": "vmess-0a2871c2",
      "server": "zmaoz.faculty.ucdavis.edu",
      "server_port": 443,
      "uuid": "7a875369-b582-425a-9f97-db3a432b444c",
      "security": "auto",
      "alter_id": 0,
      "transport": {
        "type": "ws",
        "path": "/speedtest",
        "headers": {
          "Host": "get-a-free-name.com"
        }
      },
      "tls": {
        "enabled": true,
        "insecure": true,
        "server_name": "zmaoz.faculty.ucdavis.edu"
      }
    },
    {
      "type": "vmess",
      "tag": "vmess-e1fad008",
      "server": "zmaoz.faculty.ucdavis.edu",
      "server_port": 443,
      "uuid": "07d4ef3b-1430-451a-acd9-a4d4e7c0456d",
      "security": "auto",
      "alter_id": 0,
      "transport": {
        "type": "ws",
        "path": "/speedtest",
        "headers": {
          "Host": "get-a-free-name.com"
        }
      },
      "tls": {
        "enabled": true,
        "insecure": true,
        "server_name": "zmaoz.faculty.ucdavis.edu"
      }
    },
    {
      "type": "vmess",
      "tag": "vmess-3a6ed001",
      "server": "zmaoz.faculty.ucdavis.edu",
      "server_port": 443,
      "uuid": "09f8d33b-62ae-4cb4-89eb-00e9570f30a6",
      "security": "auto",
      "alter_id": 0,
      "transport": {
        "type": "ws",
        "path": "/speedtest",
        "headers": {
          "Host": "get-a-free-name.com"
        }
      },
      "tls": {
        "enabled": true,
        "insecure": true,
        "server_name": "zmaoz.faculty.ucdavis.edu"
      }
    },
    {
      "type": "vmess",
      "tag": "vmess-3b832077",
      "server": "zmaoz.faculty.ucdavis.edu",
      "server_port": 443,
      "uuid": "298e4dd5-37b2-4021-9867-490b829cd646",
      "security": "auto",
      "alter_id": 0,
      "transport": {
        "type": "ws",
        "path": "/speedtest",
        "headers": {
          "Host": "get-a-free-name.com"
        }
      },
      "tls": {
        "enabled": true,
        "insecure": true,
        "server_name": "zmaoz.faculty.ucdavis.edu"
      }
    },
    {
      "type": "vmess",
      "tag": "vmess-cc43adc2",
      "server": "zmaoz.faculty.ucdavis.edu",
      "server_port": 443,
      "uuid": "f59c9c59-2366-4d6c-8477-b8f57568cb68",
      "security": "auto",
      "alter_id": 0,
      "transport": {
        "type": "ws",
        "path": "/speedtest",
        "headers": {
          "Host": "get-a-free-name.com"
        }
      },
      "tls": {
        "enabled": true,
        "insecure": true,
        "server_name": "zmaoz.faculty.ucdavis.edu"
      }
    },
    {
      "type": "vmess",
      "tag": "vmess-0aa52d2f",
      "server": "bwdraper.faculty.ucdavis.edu",
      "server_port": 443,
      "uuid": "80f97b15-d8ad-4863-b4ed-22f1bdc534a9",
      "security": "auto",
      "alter_id": 0,
      "transport": {
        "type": "ws",
        "path": "/speedtest",
        "headers": {
          "Host": "get-a-free-name.com"
        }
      },
      "tls": {
        "enabled": true,
        "insecure": true,
        "server_name": "bwdraper.faculty.ucdavis.edu"
      }
    },
    {
      "type": "vmess",
      "tag": "vmess-fa200099",
      "server": "bwdraper.faculty.ucdavis.edu",
      "server_port": 443,
      "uuid": "92d1a9ea-0cd8-4efb-b53f-b6496f8abef8",
      "security": "auto",
      "alter_id": 0,
      "transport": {
        "type": "ws",
        "path": "/speedtest",
        "headers": {
          "Host": "get-a-free-name.com"
        }
      },
      "tls": {
        "enabled": true,
        "insecure": true,
        "server_name": "bwdraper.faculty.ucdavis.edu"
      }
    },
    {
      "type": "vmess",
      "tag": "vmess-f969b82d",
      "server": "bwdraper.faculty.ucdavis.edu",
      "server_port": 443,
      "uuid": "0495fe07-c7fe-4af6-9827-069b32457110",
      "security": "auto",
      "alter_id": 0,
      "transport": {
        "type": "ws",
        "path": "/speedtest",
        "headers": {
          "Host": "get-a-free-name.com"
        }
      },
      "tls": {
        "enabled": true,
        "insecure": true,
        "server_name": "bwdraper.faculty.ucdavis.edu"
      }
    },
    {
      "type": "vmess",
      "tag": "vmess-0d778cda",
      "server": "bwdraper.faculty.ucdavis.edu",
      "server_port": 443,
      "uuid": "a6c590b8-12b9-4107-b840-e79d95961a70",
      "security": "auto",
      "alter_id": 0,
      "transport": {
        "type": "ws",
        "path": "/speedtest",
        "headers": {
          "Host": "get-a-free-name.com"
        }
      },
      "tls": {
        "enabled": true,
        "insecure": true,
        "server_name": "bwdraper.faculty.ucdavis.edu"
      }
    },
    {
      "type": "vmess",
      "tag": "vmess-7abf99ea",
      "server": "bwdraper.faculty.ucdavis.edu",
      "server_port": 443,
      "uuid": "f901861b-6491-450c-b500-606b2e921625",
      "security": "auto",
      "alter_id": 0,
      "transport": {
        "type": "ws",
        "path": "/speedtest",
        "headers": {
          "Host": "get-a-free-name.com"
        }
      },
      "tls": {
        "enabled": true,
        "insecure": true,
        "server_name": "bwdraper.faculty.ucdavis.edu"
      }
    },
    {
      "type": "vmess",
      "tag": "vmess-5da67203",
      "server": "pscresearch.faculty.ucdavis.edu",
      "server_port": 443,
      "uuid": "48670f89-8e15-4d5e-97db-cc2e5064b491",
      "security": "auto",
      "alter_id": 0,
      "transport": {
        "type": "ws",
        "path": "/speedtest",
        "headers": {
          "Host": "get-a-free-name.com"
        }
      },
      "tls": {
        "enabled": true,
        "insecure": true,
        "server_name": "pscresearch.faculty.ucdavis.edu"
      }
    },
    {
      "type": "vmess",
      "tag": "vmess-965b19cc",
      "server": "pscresearch.faculty.ucdavis.edu",
      "server_port": 443,
      "uuid": "5eaa121d-4362-444d-8219-29b02c35303a",
      "security": "auto",
      "alter_id": 0,
      "transport": {
        "type": "ws",
        "path": "/speedtest",
        "headers": {
          "Host": "get-a-free-name.com"
        }
      },
      "tls": {
        "enabled": true,
        "insecure": true,
        "server_name": "pscresearch.faculty.ucdavis.edu"
      }
    },
    {
      "type": "vmess",
      "tag": "vmess-38c82027",
      "server": "pscresearch.faculty.ucdavis.edu",
      "server_port": 443,
      "uuid": "649c1549-da73-406a-a184-9b4c4347d76c",
      "security": "auto",
      "alter_id": 0,
      "transport": {
        "type": "ws",
        "path": "/speedtest",
        "headers": {
          "Host": "get-a-free-name.com"
        }
      },
      "tls": {
        "enabled": true,
        "insecure": true,
        "server_name": "pscresearch.faculty.ucdavis.edu"
      }
    },
    {
      "type": "vmess",
      "tag": "vmess-e3cd4280",
      "server": "pscresearch.faculty.ucdavis.edu",
      "server_port": 443,
      "uuid": "dd7157a5-b416-49e7-b00e-8c66522f1434",
      "security": "auto",
      "alter_id": 0,
      "transport": {
        "type": "ws",
        "path": "/speedtest",
        "headers": {
          "Host": "get-a-free-name.com"
        }
      },
      "tls": {
        "enabled": true,
        "insecure": true,
        "server_name": "pscresearch.faculty.ucdavis.edu"
      }
    },
    {
      "type": "vmess",
      "tag": "vmess-91dc83f3",
      "server": "pscresearch.faculty.ucdavis.edu",
      "server_port": 443,
      "uuid": "ff006ffb-ad09-4d79-8c27-91dcd9123d8b",
      "security": "auto",
      "alter_id": 0,
      "transport": {
        "type": "ws",
        "path": "/speedtest",
        "headers": {
          "Host": "get-a-free-name.com"
        }
      },
      "tls": {
        "enabled": true,
        "insecure": true,
        "server_name": "pscresearch.faculty.ucdavis.edu"
      }
    },
    {
      "type": "vmess",
      "tag": "vmess-9a63d664",
      "server": "seminarsinmcb.faculty.ucdavis.edu",
      "server_port": 443,
      "uuid": "29221c3e-b3e9-4297-a50d-bf85a2bed80b",
      "security": "auto",
      "alter_id": 0,
      "transport": {
        "type": "ws",
        "path": "/speedtest",
        "headers": {
          "Host": "get-a-free-name.com"
        }
      },
      "tls": {
        "enabled": true,
        "insecure": true,
        "server_name": "seminarsinmcb.faculty.ucdavis.edu"
      }
    },
    {
      "type": "vmess",
      "tag": "vmess-527ac4a7",
      "server": "seminarsinmcb.faculty.ucdavis.edu",
      "server_port": 443,
      "uuid": "4f3079e5-29a3-49a0-a820-f1b08cc04f39",
      "security": "auto",
      "alter_id": 0,
      "transport": {
        "type": "ws",
        "path": "/speedtest",
        "headers": {
          "Host": "get-a-free-name.com"
        }
      },
      "tls": {
        "enabled": true,
        "insecure": true,
        "server_name": "seminarsinmcb.faculty.ucdavis.edu"
      }
    },
    {
      "type": "vmess",
      "tag": "vmess-f526d49c",
      "server": "seminarsinmcb.faculty.ucdavis.edu",
      "server_port": 443,
      "uuid": "7808b21b-b9b4-49f9-b0a8-8f507be11629",
      "security": "auto",
      "alter_id": 0,
      "transport": {
        "type": "ws",
        "path": "/speedtest",
        "headers": {
          "Host": "get-a-free-name.com"
        }
      },
      "tls": {
        "enabled": true,
        "insecure": true,
        "server_name": "seminarsinmcb.faculty.ucdavis.edu"
      }
    },
    {
      "type": "vmess",
      "tag": "vmess-d5884270",
      "server": "seminarsinmcb.faculty.ucdavis.edu",
      "server_port": 443,
      "uuid": "729922eb-2020-40a1-89f9-6eb97abcaa02",
      "security": "auto",
      "alter_id": 0,
      "transport": {
        "type": "ws",
        "path": "/speedtest",
        "headers": {
          "Host": "get-a-free-name.com"
        }
      },
      "tls": {
        "enabled": true,
        "insecure": true,
        "server_name": "seminarsinmcb.faculty.ucdavis.edu"
      }
    },
    {
      "type": "shadowsocks",
      "tag": "ss-7d8594b4",
      "server": "45.158.171.132",
      "server_port": 8080,
      "method": "chacha20-ietf-poly1305",
      "password": "4a2rfixophdjffa8KVA4Aa"
    },
    {
      "type": "shadowsocks",
      "tag": "ss-d3b11955",
      "server": "45.158.171.141",
      "server_port": 8080,
      "method": "chacha20-ietf-poly1305",
      "password": "4a2rfixophdjffa8KVA4Aa"
    },
    {
      "type": "shadowsocks",
      "tag": "ss-f07352d7",
      "server": "45.158.171.151",
      "server_port": 8080,
      "method": "chacha20-ietf-poly1305",
      "password": "4a2rfixophdjffa8KVA4Aa"
    },
    {
      "type": "shadowsocks",
      "tag": "ss-0de844c8",
      "server": "45.87.175.154",
      "server_port": 8080,
      "method": "chacha20-ietf-poly1305",
      "password": "4a2rfixophdjffa8KVA4Aa"
    }
  ],
  "route": {
    "auto_detect_interface": true,
    "final": "proxy",
    "rule_set": [
      {
        "download_detour": "direct",
        "format": "binary",
        "tag": "geosite-ads",
        "type": "remote",
        "url": "https://testingcf.jsdelivr.net/gh/MetaCubeX/meta-rules-dat@sing/geo/geosite/category-ads-all.srs"
      },
      {
        "download_detour": "direct",
        "format": "binary",
        "tag": "geosite-private",
        "type": "remote",
        "url": "https://testingcf.jsdelivr.net/gh/MetaCubeX/meta-rules-dat@sing/geo/geosite/private.srs"
      },
      {
        "download_detour": "direct",
        "format": "binary",
        "tag": "geosite-ir",
        "type": "remote",
        "url": "https://testingcf.jsdelivr.net/gh/MetaCubeX/meta-rules-dat@sing/geo/geosite/category-ir.srs"
      },
      {
        "download_detour": "direct",
        "format": "binary",
        "tag": "geoip-private",
        "type": "remote",
        "url": "https://testingcf.jsdelivr.net/gh/MetaCubeX/meta-rules-dat@sing/geo/geoip/private.srs"
      },
      {
        "download_detour": "direct",
        "format": "binary",
        "tag": "geoip-ir",
        "type": "remote",
        "url": "https://testingcf.jsdelivr.net/gh/MetaCubeX/meta-rules-dat@sing/geo/geoip/ir.srs"
      }
    ],
    "rules": [
      {
        "clash_mode": "Direct",
        "outbound": "direct"
      },
      {
        "clash_mode": "Global",
        "outbound": "proxy"
      },
      {
        "outbound": "dns-out",
        "protocol": "dns"
      },
      {
        "outbound": "direct",
        "rule_set": [
          "geoip-private",
          "geosite-private",
          "geosite-ir",
          "geoip-ir"
        ]
      },
      {
        "outbound": "block",
        "rule_set": [
          "geosite-ads"
        ]
      }
    ]
  }
}